mseep_youtube_translate_mcp-0.1.4.dist-info/licenses/LICENSE
youtube_translate_mcp/__init__.py
youtube_translate_mcp/__main__.py
youtube_translate_mcp/server.py
mseep_youtube_translate_mcp-0.1.4.dist-info/METADATA
mseep_youtube_translate_mcp-0.1.4.dist-info/WHEEL
mseep_youtube_translate_mcp-0.1.4.dist-info/entry_points.txt
mseep_youtube_translate_mcp-0.1.4.dist-info/top_level.txt
mseep_youtube_translate_mcp-0.1.4.dist-info/RECORD
